<?xml version="1.0" encoding="UTF-8"?>
<!DOCTYPE why3session PUBLIC "-//Why3//proof session v5//EN"
"https://www.why3.org/why3session.dtd">
<why3session shape_version="6">
<prover id="0" name="Alt-Ergo" version="2.5.4" timelimit="5" steplimit="0" memlimit="1000"/>
<prover id="1" name="CVC5" version="1.0.6" timelimit="5" steplimit="0" memlimit="1000"/>
<prover id="2" name="Z3" version="4.13.0" timelimit="5" steplimit="0" memlimit="1000"/>
<file format="ocaml">
<path name=".."/><path name="prova_current.ml"/>
<theory name="Prova_current">
 <goal name="cond_align_loops&#39;vc" expl="VC for cond_align_loops">
 <transf name="split_vc" >
  <goal name="cond_align_loops&#39;vc.0" expl="loop invariant init">
  <proof prover="0"><result status="timeout" time="5.000000" steps="41570"/></proof>
  <proof prover="1"><result status="timeout" time="5.000000" steps="513283"/></proof>
  <proof prover="2"><result status="unknown" time="0.001454"/></proof>
  <transf name="assert" arg1="(n_l &gt;= 1)">
   <goal name="cond_align_loops&#39;vc.0.0" expl="asserted formula" proved="true">
   <proof prover="1" timelimit="1"><result status="valid" time="0.030345" steps="23157"/></proof>
   </goal>
   <goal name="cond_align_loops&#39;vc.0.1" expl="loop invariant init">
   <proof prover="0" timelimit="1"><result status="timeout" time="1.000000" steps="25782"/></proof>
   <proof prover="1" timelimit="1"><result status="timeout" time="1.000000" steps="238797"/></proof>
   <proof prover="2" timelimit="1"><result status="unknown" time="0.000803"/></proof>
   <transf name="split_vc" >
    <goal name="cond_align_loops&#39;vc.0.1.0" expl="VC for cond_align_loops">
    <proof prover="0" timelimit="40" memlimit="2000"><result status="timeout" time="40.000000" steps="109633"/></proof>
    <proof prover="1" timelimit="1"><result status="timeout" time="1.000000" steps="229799"/></proof>
    <proof prover="2" timelimit="1"><result status="unknown" time="0.000267"/></proof>
    <transf name="assert" arg1="(n_r &gt;= 1)">
     <goal name="cond_align_loops&#39;vc.0.1.0.0" expl="asserted formula" proved="true">
     <proof prover="1" timelimit="1"><result status="valid" time="0.023551" steps="22647"/></proof>
     </goal>
     <goal name="cond_align_loops&#39;vc.0.1.0.1" expl="VC for cond_align_loops">
     <proof prover="0" timelimit="1"><result status="timeout" time="1.000000" steps="26224"/></proof>
     <proof prover="1" timelimit="1"><result status="timeout" time="1.000000" steps="194809"/></proof>
     <proof prover="2" timelimit="1"><result status="unknown" time="0.000396"/></proof>
     </goal>
    </transf>
    </goal>
    <goal name="cond_align_loops&#39;vc.0.1.1" expl="VC for cond_align_loops" proved="true">
    <proof prover="1" timelimit="1"><result status="valid" time="0.032318" steps="23215"/></proof>
    </goal>
   </transf>
   </goal>
  </transf>
  </goal>
  <goal name="cond_align_loops&#39;vc.1" expl="loop invariant init" proved="true">
  <proof prover="1" timelimit="1"><result status="valid" time="0.045432" steps="23273"/></proof>
  </goal>
  <goal name="cond_align_loops&#39;vc.2" expl="loop invariant init" proved="true">
  <proof prover="0"><result status="valid" time="0.017779" steps="25"/></proof>
  </goal>
  <goal name="cond_align_loops&#39;vc.3" expl="loop invariant init" proved="true">
  <proof prover="1"><result status="valid" time="0.024737" steps="22730"/></proof>
  </goal>
  <goal name="cond_align_loops&#39;vc.4" expl="loop invariant init" proved="true">
  <proof prover="1"><result status="valid" time="0.025375" steps="22736"/></proof>
  </goal>
  <goal name="cond_align_loops&#39;vc.5" expl="loop invariant init" proved="true">
  <proof prover="1"><result status="valid" time="0.042663" steps="24538"/></proof>
  </goal>
  <goal name="cond_align_loops&#39;vc.6" expl="precondition" proved="true">
  <proof prover="1"><result status="valid" time="0.038575" steps="24024"/></proof>
  </goal>
  <goal name="cond_align_loops&#39;vc.7" expl="precondition" proved="true">
  <proof prover="1"><result status="valid" time="0.043622" steps="24665"/></proof>
  </goal>
  <goal name="cond_align_loops&#39;vc.8" expl="loop variant decrease" proved="true">
  <proof prover="0"><result status="valid" time="0.021842" steps="66"/></proof>
  </goal>
  <goal name="cond_align_loops&#39;vc.9" expl="loop invariant preservation">
  <proof prover="0"><result status="timeout" time="5.000000" steps="66657"/></proof>
  <proof prover="1"><result status="timeout" time="5.000000" steps="369038"/></proof>
  <proof prover="2"><result status="unknown" time="0.000125"/></proof>
  </goal>
  <goal name="cond_align_loops&#39;vc.10" expl="loop invariant preservation" proved="true">
  <proof prover="1"><result status="valid" time="0.049021" steps="25020"/></proof>
  </goal>
  <goal name="cond_align_loops&#39;vc.11" expl="loop invariant preservation" proved="true">
  <proof prover="0"><result status="valid" time="0.028867" steps="68"/></proof>
  </goal>
  <goal name="cond_align_loops&#39;vc.12" expl="loop invariant preservation" proved="true">
  <proof prover="1"><result status="valid" time="0.067677" steps="26367"/></proof>
  </goal>
  <goal name="cond_align_loops&#39;vc.13" expl="loop invariant preservation" proved="true">
  <proof prover="1"><result status="valid" time="0.081703" steps="26444"/></proof>
  </goal>
  <goal name="cond_align_loops&#39;vc.14" expl="loop invariant preservation">
  <proof prover="0"><result status="timeout" time="5.000000" steps="43559"/></proof>
  <proof prover="1"><result status="timeout" time="5.000000" steps="369850"/></proof>
  <proof prover="2"><result status="unknown" time="0.000300"/></proof>
  <transf name="destruct_rec" arg1="H8">
   <goal name="cond_align_loops&#39;vc.14.0" expl="loop invariant preservation">
   <proof prover="0" timelimit="1"><result status="timeout" time="1.000000" steps="17986"/></proof>
   <proof prover="1" timelimit="1"><result status="timeout" time="1.000000" steps="210427"/></proof>
   <proof prover="2" timelimit="1"><result status="unknown" time="0.000369"/></proof>
   <transf name="split_vc" >
    <goal name="cond_align_loops&#39;vc.14.0.0" expl="loop invariant preservation">
    <proof prover="0" timelimit="1"><result status="timeout" time="1.000000" steps="18951"/></proof>
    <proof prover="1" timelimit="1"><result status="timeout" time="1.000000" steps="219908"/></proof>
    <proof prover="2" timelimit="1"><result status="unknown" time="0.000307"/></proof>
    <transf name="split_vc" >
     <goal name="cond_align_loops&#39;vc.14.0.0.0" expl="loop invariant preservation">
     <proof prover="0" timelimit="10" memlimit="4000"><result status="timeout" time="10.000000" steps="84423"/></proof>
     <proof prover="1" timelimit="10" memlimit="4000"><result status="timeout" time="10.000000" steps="559611"/></proof>
     <proof prover="2" timelimit="10" memlimit="4000"><result status="unknown" time="0.000231"/></proof>
     </goal>
     <goal name="cond_align_loops&#39;vc.14.0.0.1" expl="loop invariant preservation" proved="true">
     <proof prover="1" timelimit="1"><result status="valid" time="0.024250" steps="24235"/></proof>
     </goal>
    </transf>
    </goal>
    <goal name="cond_align_loops&#39;vc.14.0.1" expl="loop invariant preservation" proved="true">
    <proof prover="1" timelimit="1"><result status="valid" time="0.037043" steps="24224"/></proof>
    </goal>
   </transf>
   </goal>
   <goal name="cond_align_loops&#39;vc.14.1" expl="loop invariant preservation" proved="true">
   <proof prover="1" timelimit="1"><result status="valid" time="0.032954" steps="24287"/></proof>
   </goal>
   <goal name="cond_align_loops&#39;vc.14.2" expl="loop invariant preservation" proved="true">
   <proof prover="1" timelimit="1"><result status="valid" time="0.027734" steps="24287"/></proof>
   </goal>
   <goal name="cond_align_loops&#39;vc.14.3" expl="loop invariant preservation">
   <proof prover="0" timelimit="1"><result status="timeout" time="1.000000" steps="15815"/></proof>
   <proof prover="1" timelimit="1"><result status="timeout" time="1.000000" steps="210604"/></proof>
   <proof prover="2" timelimit="1"><result status="unknown" time="0.000337"/></proof>
   <transf name="split_vc" >
    <goal name="cond_align_loops&#39;vc.14.3.0" expl="loop invariant preservation">
    <proof prover="0" timelimit="1"><result status="timeout" time="1.000000" steps="14635"/></proof>
    <proof prover="1" timelimit="1"><result status="timeout" time="1.000000" steps="208474"/></proof>
    <proof prover="2" timelimit="1"><result status="unknown" time="0.000224"/></proof>
    <transf name="split_vc" >
     <goal name="cond_align_loops&#39;vc.14.3.0.0" expl="loop invariant preservation">
     <proof prover="0" timelimit="10" memlimit="4000"><result status="timeout" time="10.000000" steps="77408"/></proof>
     <proof prover="1" timelimit="10" memlimit="4000"><result status="timeout" time="10.000000" steps="566374"/></proof>
     <proof prover="2" timelimit="10" memlimit="4000"><result status="unknown" time="0.000470"/></proof>
     </goal>
     <goal name="cond_align_loops&#39;vc.14.3.0.1" expl="loop invariant preservation" proved="true">
     <proof prover="1" timelimit="1"><result status="valid" time="0.030519" steps="24238"/></proof>
     </goal>
    </transf>
    </goal>
    <goal name="cond_align_loops&#39;vc.14.3.1" expl="loop invariant preservation" proved="true">
    <proof prover="1" timelimit="1"><result status="valid" time="0.028769" steps="24216"/></proof>
    </goal>
   </transf>
   </goal>
  </transf>
  </goal>
  <goal name="cond_align_loops&#39;vc.15" expl="loop variant decrease" proved="true">
  <proof prover="1"><result status="valid" time="0.047411" steps="24962"/></proof>
  </goal>
  <goal name="cond_align_loops&#39;vc.16" expl="loop invariant preservation">
  <proof prover="0"><result status="timeout" time="5.000000" steps="64589"/></proof>
  <proof prover="1"><result status="timeout" time="5.000000" steps="366908"/></proof>
  <proof prover="2"><result status="unknown" time="0.000073"/></proof>
  </goal>
  <goal name="cond_align_loops&#39;vc.17" expl="loop invariant preservation" proved="true">
  <proof prover="0"><result status="valid" time="0.018784" steps="54"/></proof>
  </goal>
  <goal name="cond_align_loops&#39;vc.18" expl="loop invariant preservation" proved="true">
  <proof prover="1"><result status="valid" time="0.022693" steps="24170"/></proof>
  </goal>
  <goal name="cond_align_loops&#39;vc.19" expl="loop invariant preservation" proved="true">
  <proof prover="0"><result status="valid" time="0.021751" steps="55"/></proof>
  </goal>
  <goal name="cond_align_loops&#39;vc.20" expl="loop invariant preservation" proved="true">
  <proof prover="1"><result status="valid" time="0.036287" steps="24185"/></proof>
  </goal>
  <goal name="cond_align_loops&#39;vc.21" expl="loop invariant preservation">
  <proof prover="0"><result status="timeout" time="5.000000" steps="44918"/></proof>
  <proof prover="1"><result status="timeout" time="5.000000" steps="370331"/></proof>
  <proof prover="2"><result status="unknown" time="0.000380"/></proof>
  </goal>
  <goal name="cond_align_loops&#39;vc.22" expl="precondition" proved="true">
  <proof prover="1"><result status="valid" time="0.027471" steps="24083"/></proof>
  </goal>
  <goal name="cond_align_loops&#39;vc.23" expl="precondition" proved="true">
  <proof prover="0"><result status="valid" time="0.032606" steps="48"/></proof>
  </goal>
  <goal name="cond_align_loops&#39;vc.24" expl="loop variant decrease" proved="true">
  <proof prover="1"><result status="valid" time="0.050484" steps="25075"/></proof>
  </goal>
  <goal name="cond_align_loops&#39;vc.25" expl="loop invariant preservation">
  <proof prover="0"><result status="timeout" time="5.000000" steps="68852"/></proof>
  <proof prover="1"><result status="timeout" time="5.000000" steps="368680"/></proof>
  <proof prover="2"><result status="unknown" time="0.000423"/></proof>
  </goal>
  <goal name="cond_align_loops&#39;vc.26" expl="loop invariant preservation" proved="true">
  <proof prover="1"><result status="valid" time="0.040519" steps="25094"/></proof>
  </goal>
  <goal name="cond_align_loops&#39;vc.27" expl="loop invariant preservation" proved="true">
  <proof prover="0"><result status="valid" time="0.026276" steps="62"/></proof>
  </goal>
  <goal name="cond_align_loops&#39;vc.28" expl="loop invariant preservation">
  <proof prover="0"><result status="timeout" time="5.000000" steps="64397"/></proof>
  <proof prover="1"><result status="timeout" time="5.000000" steps="368348"/></proof>
  <proof prover="2"><result status="unknown" time="0.000439"/></proof>
  </goal>
  <goal name="cond_align_loops&#39;vc.29" expl="loop invariant preservation" proved="true">
  <proof prover="1"><result status="valid" time="0.037791" steps="25183"/></proof>
  </goal>
  <goal name="cond_align_loops&#39;vc.30" expl="loop invariant preservation">
  <proof prover="0"><result status="timeout" time="5.000000" steps="47621"/></proof>
  <proof prover="1"><result status="timeout" time="5.000000" steps="371767"/></proof>
  <proof prover="2"><result status="unknown" time="0.000286"/></proof>
  </goal>
  <goal name="cond_align_loops&#39;vc.31" expl="loop variant decrease" proved="true">
  <proof prover="1"><result status="valid" time="0.044967" steps="25046"/></proof>
  </goal>
  <goal name="cond_align_loops&#39;vc.32" expl="loop invariant preservation">
  <proof prover="0"><result status="timeout" time="5.000000" steps="76616"/></proof>
  <proof prover="1"><result status="timeout" time="5.000000" steps="365999"/></proof>
  <proof prover="2"><result status="unknown" time="0.000316"/></proof>
  </goal>
  <goal name="cond_align_loops&#39;vc.33" expl="loop invariant preservation" proved="true">
  <proof prover="0"><result status="valid" time="0.024900" steps="56"/></proof>
  </goal>
  <goal name="cond_align_loops&#39;vc.34" expl="loop invariant preservation" proved="true">
  <proof prover="1"><result status="valid" time="0.030341" steps="24229"/></proof>
  </goal>
  <goal name="cond_align_loops&#39;vc.35" expl="loop invariant preservation" proved="true">
  <proof prover="0"><result status="valid" time="0.033330" steps="57"/></proof>
  </goal>
  <goal name="cond_align_loops&#39;vc.36" expl="loop invariant preservation" proved="true">
  <proof prover="1"><result status="valid" time="0.039200" steps="24244"/></proof>
  </goal>
  <goal name="cond_align_loops&#39;vc.37" expl="loop invariant preservation">
  <proof prover="0"><result status="timeout" time="5.000000" steps="53669"/></proof>
  <proof prover="1"><result status="timeout" time="5.000000" steps="370376"/></proof>
  <proof prover="2"><result status="unknown" time="0.000059"/></proof>
  </goal>
  <goal name="cond_align_loops&#39;vc.38" expl="assertion">
  <proof prover="0"><result status="timeout" time="5.000000" steps="632"/></proof>
  <proof prover="1"><result status="timeout" time="5.000000" steps="370500"/></proof>
  <proof prover="2"><result status="unknown" time="0.000323"/></proof>
  </goal>
  <goal name="cond_align_loops&#39;vc.39" expl="precondition" proved="true">
  <proof prover="0"><result status="valid" time="0.027576" steps="42"/></proof>
  </goal>
  <goal name="cond_align_loops&#39;vc.40" expl="loop variant decrease" proved="true">
  <proof prover="1"><result status="valid" time="0.043044" steps="25328"/></proof>
  </goal>
  <goal name="cond_align_loops&#39;vc.41" expl="loop invariant preservation">
  <proof prover="0"><result status="timeout" time="5.000000" steps="46097"/></proof>
  <proof prover="1"><result status="timeout" time="5.000000" steps="375368"/></proof>
  <proof prover="2"><result status="unknown" time="0.000093"/></proof>
  </goal>
  <goal name="cond_align_loops&#39;vc.42" expl="loop invariant preservation" proved="true">
  <proof prover="0"><result status="valid" time="0.030213" steps="136"/></proof>
  </goal>
  <goal name="cond_align_loops&#39;vc.43" expl="loop invariant preservation" proved="true">
  <proof prover="0"><result status="valid" time="0.025541" steps="98"/></proof>
  </goal>
  <goal name="cond_align_loops&#39;vc.44" expl="loop invariant preservation">
  <proof prover="0"><result status="timeout" time="5.000000" steps="45555"/></proof>
  <proof prover="1"><result status="timeout" time="5.000000" steps="372202"/></proof>
  <proof prover="2"><result status="unknown" time="0.000259"/></proof>
  </goal>
  <goal name="cond_align_loops&#39;vc.45" expl="loop invariant preservation" proved="true">
  <proof prover="1"><result status="valid" time="0.059036" steps="25553"/></proof>
  </goal>
  <goal name="cond_align_loops&#39;vc.46" expl="loop invariant preservation" proved="true">
  <proof prover="1"><result status="valid" time="0.070364" steps="27748"/></proof>
  </goal>
  <goal name="cond_align_loops&#39;vc.47" expl="loop variant decrease" proved="true">
  <proof prover="1"><result status="valid" time="0.049816" steps="25187"/></proof>
  </goal>
  <goal name="cond_align_loops&#39;vc.48" expl="loop invariant preservation">
  <proof prover="0"><result status="timeout" time="5.000000" steps="5310"/></proof>
  <proof prover="1"><result status="timeout" time="5.000000" steps="371665"/></proof>
  <proof prover="2"><result status="unknown" time="0.000001"/></proof>
  </goal>
  <goal name="cond_align_loops&#39;vc.49" expl="loop invariant preservation" proved="true">
  <proof prover="0"><result status="valid" time="0.026098" steps="78"/></proof>
  </goal>
  <goal name="cond_align_loops&#39;vc.50" expl="loop invariant preservation" proved="true">
  <proof prover="0"><result status="valid" time="0.027701" steps="62"/></proof>
  </goal>
  <goal name="cond_align_loops&#39;vc.51" expl="loop invariant preservation" proved="true">
  <proof prover="1"><result status="valid" time="0.025819" steps="24329"/></proof>
  </goal>
  <goal name="cond_align_loops&#39;vc.52" expl="loop invariant preservation" proved="true">
  <proof prover="0"><result status="valid" time="0.022740" steps="62"/></proof>
  </goal>
  <goal name="cond_align_loops&#39;vc.53" expl="loop invariant preservation" proved="true">
  <proof prover="0"><result status="valid" time="0.018810" steps="62"/></proof>
  </goal>
  <goal name="cond_align_loops&#39;vc.54" expl="postcondition" proved="true">
  <proof prover="0"><result status="valid" time="0.019108" steps="44"/></proof>
  </goal>
 </transf>
 </goal>
</theory>
</file>
</why3session>
